[{"code":"WCP","name":"Whitecap Resources Inc.","close":11.45,"market_capitalization":14.058120192,"dividend_yield":6.3,"payout_ratio":0.6457,"pe_ratio":10.247787,"earnings_share":1.13,"beta":0.885,"volume_avg_30d":6035.806,"52_week_high":11.91,"52_week_low":6.87,"ex_dividend_date":1764288000,"next_div_date":"2025-11-28T00:00:00.000","days_until_exdiv":1,"pct_from_52w_low":66.6666666667},{"code":"SU","name":"Suncor Energy Inc.","close":62.52,"market_capitalization":75.730853888,"dividend_yield":3.84,"payout_ratio":0.53150004,"pe_ratio":14.550117,"earnings_share":4.29,"beta":0.793,"volume_avg_30d":7216.353,"52_week_high":64.14,"52_week_low":43.59,"ex_dividend_date":1764720000,"next_div_date":"2025-12-03T00:00:00.000","days_until_exdiv":6,"pct_from_52w_low":43.4273916036},{"code":"GWO","name":"Great-West Lifeco Inc.","close":64.56,"market_capitalization":59.859603456,"dividend_yield":3.77,"payout_ratio":0.5534,"pe_ratio":15.018562,"earnings_share":4.31,"beta":0.715,"volume_avg_30d":1604.522,"52_week_high":65.0,"52_week_low":44.89,"ex_dividend_date":1764720000,"next_div_date":"2025-12-03T00:00:00.000","days_until_exdiv":6,"pct_from_52w_low":43.8182223212},{"code":"OTEX","name":"Open Text Corporation","close":47.62,"market_capitalization":12.062240768,"dividend_yield":3.17,"payout_ratio":0.5563,"pe_ratio":17.63197,"earnings_share":2.69,"beta":1.076,"volume_avg_30d":1076.866,"52_week_high":56.0,"52_week_low":32.41,"ex_dividend_date":1764892800,"next_div_date":"2025-12-05T00:00:00.000","days_until_exdiv":8,"pct_from_52w_low":46.9299598889},{"code":"RCI.B","name":"Rogers Communications Inc.","close":54.24,"market_capitalization":29.900828672,"dividend_yield":3.64,"payout_ratio":0.1604,"pe_ratio":4.4065757,"earnings_share":12.47,"beta":0.828,"volume_avg_30d":1926.006,"52_week_high":56.15,"52_week_low":32.42,"ex_dividend_date":1765152000,"next_div_date":"2025-12-08T00:00:00.000","days_until_exdiv":11,"pct_from_52w_low":67.3041332511},{"code":"MFI","name":"Maple Leaf Foods Inc.","close":25.11,"market_capitalization":3.125710336,"dividend_yield":3.63,"payout_ratio":0.6065,"pe_ratio":16.167742,"earnings_share":1.55,"beta":1.019,"volume_avg_30d":323.69,"52_week_high":32.31111,"52_week_low":17.43111,"ex_dividend_date":1765324800,"next_div_date":"2025-12-10T00:00:00.000","days_until_exdiv":13,"pct_from_52w_low":44.0527883766},{"code":"CVE","name":"Cenovus Energy Inc.","close":24.56,"market_capitalization":46.537555968,"dividend_yield":3.24,"payout_ratio":0.4393,"pe_ratio":14.260116,"earnings_share":1.73,"beta":0.722,"volume_avg_30d":10957.732,"52_week_high":26.36,"52_week_low":14.48,"ex_dividend_date":1765756800,"next_div_date":"2025-12-15T00:00:00.000","days_until_exdiv":18,"pct_from_52w_low":69.6132596685},{"code":"IGM","name":"IGM Financial Inc.","close":57.28,"market_capitalization":13.573706752,"dividend_yield":3.92,"payout_ratio":0.5172,"pe_ratio":13.209195,"earnings_share":4.35,"beta":1.17,"volume_avg_30d":319.064,"52_week_high":57.755,"52_week_low":38.89,"ex_dividend_date":1767052800,"next_div_date":"2025-12-30T00:00:00.000","days_until_exdiv":33,"pct_from_52w_low":47.2872203651},{"code":"HWX","name":"Headwater Exploration Inc.","close":8.73,"market_capitalization":2.09156288,"dividend_yield":5.02,"payout_ratio":0.589,"pe_ratio":12.0,"earnings_share":0.73,"beta":1.085,"volume_avg_30d":667.209,"52_week_high":9.15,"52_week_low":4.75,"ex_dividend_date":1767139200,"next_div_date":"2025-12-31T00:00:00.000","days_until_exdiv":34,"pct_from_52w_low":83.7894736842},{"code":"NTR","name":"Nutrien Ltd.","close":80.11,"market_capitalization":39.142817792,"dividend_yield":3.82,"payout_ratio":0.5863,"pe_ratio":15.374046,"earnings_share":5.24,"beta":1.146,"volume_avg_30d":1729.8,"52_week_high":88.03,"52_week_low":62.89,"ex_dividend_date":1767139200,"next_div_date":"2025-12-31T00:00:00.000","days_until_exdiv":34,"pct_from_52w_low":27.3811416759},{"code":"POW","name":"Power Corporation of Canada","close":72.03,"market_capitalization":45.96406272,"dividend_yield":3.4,"payout_ratio":0.50630003,"pe_ratio":15.22152,"earnings_share":4.74,"beta":0.987,"volume_avg_30d":2377.361,"52_week_high":72.49,"52_week_low":41.88,"ex_dividend_date":1767139200,"next_div_date":"2025-12-31T00:00:00.000","days_until_exdiv":34,"pct_from_52w_low":71.9914040115}]